treadscan/__init__.py
treadscan/detector.py
treadscan/extractor.py
treadscan/segmentor.py
treadscan/utilities.py
treadscan-1.0.0.dist-info/LICENSE
treadscan-1.0.0.dist-info/METADATA
treadscan-1.0.0.dist-info/WHEEL
treadscan-1.0.0.dist-info/top_level.txt
treadscan-1.0.0.dist-info/RECORD
