Metadata-Version: 2.1
Name: treadscan
Version: 1.0.0
Summary: Tools for scanning tire tread(s).
Home-page: https://github.com/bohundan/treadscan
Author: Daniel Bohuněk
Author-email: bohundan@fit.cvut.cz
Project-URL: Bug Tracker, https://github.com/bohundan/treadscan/issues
Project-URL: Documentation, https://treadscan.readthedocs.io/
Classifier: Programming Language :: Python :: 3
Classifier: License :: OSI Approved :: MIT License
Classifier: Operating System :: OS Independent
Requires-Python: >=3.8
License-File: LICENSE
Requires-Dist: improutils
Requires-Dist: numpy
Requires-Dist: opencv-python
Requires-Dist: opencv-contrib-python
Requires-Dist: torch
Requires-Dist: torchvision
